alu.v
//=========================================================================
// Name & Email must be EXACTLY as in Gradescope roster!
// Name: Isaac Lee      
// Email: ilee002@ucr.edu
// 
// Assignment name: Lab02ALU
// Lab section: 21
// TA: Sakshar Chakravarty
// 
// I hereby certify that I have not received assistance on this assignment,
// or used code, from ANY outside source other than the instruction team
// (apart from what was provided in the starter file).
//
//=========================================================================

`timescale 1ns / 1ps

// --------------------------------------
// MIPS ALU Control & Funct constants
// --------------------------------------

`define ALU_AND         4'b0000
`define ALU_OR          4'b0001
`define ALU_ADD         4'b0010
`define ALU_SUBTRACT    4'b0110
`define ALU_LESS_THAN   4'b0111
`define ALU_NOR         4'b1100
  
`define FUNCT_AND       6'b100100
`define FUNCT_OR        6'b100101
`define FUNCT_ADD       6'b100000
`define FUNCT_SUBTRACT 	6'b100010
`define FUNCT_LESS_THAN 6'b101010
`define FUNCT_NOR 		6'b100111


`define WORD_SIZE 32 

module alu (
    input  [3:0] alu_control,  // ALU control from alu_control.v
    input  [31:0] A,           // Operand A
    input  [31:0] B,           // Operand B
    output reg [31:0] result,  // Result
    output reg        zero     // Zero flag
);

// ---------------------------------------------------------
// Implementation of MIPS ALU 
// --------------------------------------------------------- 


    always @(*) begin
        case (alu_control)
            4'b0000: result = A & B;                   // AND
            4'b0001: result = A | B;                   // OR
            4'b0010: result = A + B;                   // ADD
            4'b0110: result = A - B;                   // SUB
            4'b0111: result = ($signed(A) < $signed(B)) ? 32'd1 : 32'd0; //signed SLT
            4'b1100: result = ~(A | B);                // NOR
            default: result = 32'b0;                   // shouldn't happen
        endcase
        zero = (result == 32'b0);
    end

endmodule

alu_control.v
//=========================================================================
// Name & Email must be EXACTLY as in Gradescope roster!
// Name: 
// Email: 
// 
// Assignment name: 
// Lab section: 
// TA: 
// 
// I hereby certify that I have not received assistance on this assignment,
// or used code, from ANY outside source other than the instruction team
// (apart from what was provided in the starter file).
//
//=========================================================================

// --------------------------------------
// MIPS ALU Control & Funct constants
// --------------------------------------

`define ALU_AND         4'b0000
`define ALU_OR          4'b0001
`define ALU_ADD         4'b0010
`define ALU_SUBTRACT    4'b0110
`define ALU_LESS_THAN   4'b0111
`define ALU_NOR         4'b1100
  
`define FUNCT_AND       6'b100100
`define FUNCT_OR        6'b100101
`define FUNCT_ADD       6'b100000
`define FUNCT_SUBTRACT 	6'b100010
`define FUNCT_LESS_THAN 6'b101010
`define FUNCT_NOR 		6'b100111

module alu_control (
    input  wire [1:0] alu_op, 
    input  wire [5:0] funct, 
    output reg [3:0] alu_control
    );

// ------------------------------
// Insert your solution below
// ------------------------------ 

always @(alu_op or funct) begin 

    if (alu_op == 2'b00) begin // LW and SW 
        alu_control = `ALU_ADD ; 
    end else if (alu_op == 2'b01) begin  // Branch 
        alu_control = `ALU_SUBTRACT ; 
    end else begin
        case (funct)   // R Type Instruction 
            `FUNCT_AND :       alu_control = `ALU_AND ; 
            `FUNCT_OR  :       alu_control = `ALU_OR ; 
            `FUNCT_ADD :       alu_control = `ALU_ADD ; 
            `FUNCT_SUBTRACT :  alu_control = `ALU_SUBTRACT ; 
            `FUNCT_LESS_THAN : alu_control = `ALU_LESS_THAN ; 
            `FUNCT_NOR :       alu_control = `ALU_NOR ; 
            default :          alu_control = `ALU_ADD ;      
        endcase 
	end // End else 
end  // End block 

endmodule

control.v
//=========================================================================
// Name & Email must be EXACTLY as in Gradescope roster!
// Name: Isaac Lee  
// Email: ilee002@ucr.edu
// 
// Assignment name: Lab03-DatapathControlUnit
// Lab section: 21
// TA: Sakshar Chakravarty
// 
// I hereby certify that I have not received assistance on this assignment,
// or used code, from ANY outside source other than the instruction team
// (apart from what was provided in the starter file).
//
//=========================================================================

// --------------------------------------
// Opcodes 
// --------------------------------------

`define OPCODE_R_TYPE       6'b000000
`define OPCODE_LOAD_WORD    6'b100011
`define OPCODE_STORE_WORD   6'b101011
`define OPCODE_BRANCH_EQ    6'b000100
`define OPCODE_ADDI         6'b001000

module control  (
    input  wire [5:0] instr_op, 
    output reg       reg_dst,   
    output reg       branch,     
    output reg       mem_read,  
    output reg       mem_to_reg,
    output reg [1:0] alu_op,        
    output reg       mem_write, 
    output reg       alu_src,    
    output reg       reg_write
    );

// ------------------------------
// Insert your solution below
// ------------------------------ 
always @(instr_op) begin
    case (instr_op)

        `OPCODE_R_TYPE: begin
            reg_dst    = 1;
            alu_src    = 0;
            mem_to_reg = 0;
            reg_write  = 1;
            mem_read   = 0;
            mem_write  = 0;
            branch     = 0;
            alu_op     = 2'b10;
        end

        `OPCODE_LOAD_WORD: begin
            reg_dst    = 0;
            alu_src    = 1;
            mem_to_reg = 1;
            reg_write  = 1;
            mem_read   = 1;
            mem_write  = 0;
            branch     = 0;
            alu_op     = 2'b00;
        end

        `OPCODE_STORE_WORD: begin
            reg_dst    = 0; // “X” → set 0
            alu_src    = 1;
            mem_to_reg = 0; // “X” → set 0
            reg_write  = 0;
            mem_read   = 0;
            mem_write  = 1;
            branch     = 0;
            alu_op     = 2'b00;
        end

        `OPCODE_BRANCH_EQ: begin
            reg_dst    = 0; // “X”
            alu_src    = 0;
            mem_to_reg = 0; // “X”
            reg_write  = 0;
            mem_read   = 0;
            mem_write  = 0;
            branch     = 1;
            alu_op     = 2'b01;
        end

        `OPCODE_ADDI: begin
            reg_dst    = 0;
            alu_src    = 1;
            mem_to_reg = 0;
            reg_write  = 1;
            mem_read   = 0;
            mem_write  = 0;
            branch     = 0;
            alu_op     = 2'b00;
        end

        default: begin
            // safe defaults (treat as NOP)
            reg_dst    = 0;
            alu_src    = 0;
            mem_to_reg = 0;
            reg_write  = 0;
            mem_read   = 0;
            mem_write  = 0;
            branch     = 0;
            alu_op     = 2'b00;
        end
    endcase
end
endmodule

lab03_tb.v
//=========================================================================
// Name & Email must be EXACTLY as in Gradescope roster!
// Name: Isaac Lee  
// Email: ilee002@ucr.edu
// 
// Assignment name: Lab03-DatapathControlUnit
// Lab section: 21
// TA: Sakshar Chakravarty
// 
// I hereby certify that I have not received assistance on this assignment,
// or used code, from ANY outside source other than the instruction team
// (apart from what was provided in the starter file).
//
//=========================================================================

`timescale 1ns / 1ps

module datapath_tb;
    // Inputs
    reg clk; 
    reg [31:0] instruction;
    reg [31:0] A;
    reg [31:0] B;

    wire reg_dst;
    wire branch;
    wire mem_read;
    wire mem_to_reg;
    wire [1:0] alu_op;
    wire mem_write;
    wire alu_src;
    wire reg_write;

    wire zero;
    wire [31:0] result;
    wire [3:0] alu_ctrl;

    // -------------------------------------------------------
    // Setup output file for possible debugging uses
    // -------------------------------------------------------
    initial
    begin
        $dumpfile("lab03.vcd");
        $dumpvars(0);
    end
    
    // ---------------------------------------------------
    // Instantiate the Units Under Test (UUT)
    // --------------------------------------------------- 
    
    control control_uut (
        .instr_op(instruction[31:26]),
        .reg_dst(reg_dst),
        .branch(branch),
        .mem_read(mem_read),
        .mem_to_reg(mem_to_reg),
        .alu_op(alu_op),
        .mem_write(mem_write),
        .alu_src(alu_src),
        .reg_write(reg_write)
    );

    alu_control alu_control_uut (
        .alu_op(alu_op),
        .funct(instruction[5:0]),
        .alu_control(alu_ctrl)
    );

    alu alu_uut (
        .alu_control(alu_ctrl),
        .A(A),
        .B(B),
        .zero(zero),
        .result(result)
    );

    initial begin 
        clk = 0; #50
        clk = 1; #50
        clk = 0; #50
        clk = 1; #50
        
        forever begin 
            clk = ~clk; #50; 
        end 
    end

    task test_case(
        input [31:0] instruction_val,
        input [31:0] A_val,
        input [31:0] B_val,
        input        zero_val,
        input [31:0] result_val,
        input        reg_dst_val,
        input        branch_val,
        input        mem_read_val,
        input        mem_to_reg_val,
        input [1:0]  alu_op_val,
        input        mem_write_val,
        input        alu_src_val,
        input        reg_write_val);
        begin
            totalTests = totalTests + 1;
            instruction = instruction_val;
            A = A_val;
            B = B_val;

            #100; // Wait 
            if (result_val     !== result       || 
                zero_val       !== zero         || 
                reg_dst_val    !== reg_dst      || 
                branch_val     !== branch       || 
                mem_read_val   !== mem_read     || 
                mem_to_reg_val !== mem_to_reg   || 
                alu_op_val     !== alu_op       || 
                mem_write_val  !== mem_write    || 
                alu_src_val    !== alu_src      || 
                reg_write_val  !== reg_write) 
            begin
                $write("\nfailed - expected: zero = %b, result = %h, reg_dst = %b, branch = %b, mem_read = %b, mem_to_reg = %b, alu_op = %b, mem_write = %b, alu_src = %b, reg_write = %b", 
                       zero_val, result_val, reg_dst_val, branch_val, mem_read_val, mem_to_reg_val, alu_op_val, mem_write_val, alu_src_val, reg_write_val);
                $write("\n       - actual  : zero = %b, result = %h, reg_dst = %b, branch = %b, mem_read = %b, mem_to_reg = %b, alu_op = %b, mem_write = %b, alu_src = %b, reg_write = %b\n", 
                       zero, result, reg_dst, branch, mem_read, mem_to_reg, alu_op, mem_write, alu_src, reg_write);
                failedTests = failedTests + 1;
            end else begin
                $write("passed\n");
            end
            #10; // Wait 
        end
    endtask


    integer failedTests = 0;
    integer totalTests = 0;
    initial begin
        // Reset
        @(posedge clk); // Wait for first clock out of reset 
        #10; // Wait 

        // -------------------------------------------------------
        // Control-unit tests
        // -------------------------------------------------------

        // R-type AND
        test_case(32'h00000024, 32'hFFFFFFFF, 32'h00000001,
                  1'b0, 32'h00000001, 1'b1, 1'b0, 1'b0, 1'b0, 2'b10, 1'b0, 1'b0, 1'b1);

        // R-type AND zero
        test_case(32'h00000025, 32'hFFFFFFFF, 32'h00000001,
                  1'b0, 32'hFFFFFFFF, 1'b1, 1'b0, 1'b0, 1'b0, 2'b10, 1'b0, 1'b0, 1'b1);

        // R-type ADD
        test_case(32'h00000020, 32'hFFFFFFFF, 32'h00000001,
                  1'b1, 32'h00000000, 1'b1, 1'b0, 1'b0, 1'b0, 2'b10, 1'b0, 1'b0, 1'b1);

        // R-type SUB
        test_case(32'h00000022, 32'hFFFFFFFF, 32'h00000001,
                  1'b0, 32'hFFFFFFFE, 1'b1, 1'b0, 1'b0, 1'b0, 2'b10, 1'b0, 1'b0, 1'b1);

        // R-type SLT (equal)
        test_case(32'h0000002A, 32'hFFFFFFFF, 32'h00000001,
                  1'b0, 32'h00000001, 1'b1, 1'b0, 1'b0, 1'b0, 2'b10, 1'b0, 1'b0, 1'b1);

        // R-type NOR
        test_case(32'h00000027, 32'h0000FFFF, 32'hFFFF0000,
                  1'b1, 32'h00000000, 1'b1, 1'b0, 1'b0, 1'b0, 2'b10, 1'b0, 1'b0, 1'b1);

        // addi
        test_case(32'h20000004, 32'hFFFFFFFB, 32'h00000004,
                  1'b0, 32'hFFFFFFFF, 1'b0, 1'b0, 1'b0, 1'b0, 2'b00, 1'b0, 1'b1, 1'b1);

        // lw
        test_case(32'h8C000020, 32'h000000FF, 32'h00000020,
                  1'b0, 32'h0000011F, 1'b0, 1'b0, 1'b1, 1'b1, 2'b00, 1'b0, 1'b1, 1'b1);

        // sw
        test_case(32'hAC000064, 32'h000000FF, 32'h00000064,
                  1'b0, 32'h00000163, 1'b0, 1'b0, 1'b0, 1'b0, 2'b00, 1'b1, 1'b1, 1'b0);

        // beq
        test_case(32'h10000025, 32'h000000FF, 32'h00000025,
                  1'b0, 32'h000000DA, 1'b0, 1'b1, 1'b0, 1'b0, 2'b01, 1'b0, 1'b0, 1'b0);

        // -------------------------------------------------------
        // Test group 2: ALU Control Unit
        // -------------------------------------------------------
        $write("\tTest Case 1: R-type (add) ...");
        test_case(32'h00000024, 32'hFFFFFFFF, 32'h0001, 1'b0, 32'h0001, 1'b1, 1'b0, 1'b0, 1'b0, 2'b10, 1'b0, 1'b0, 1'b1);

        // -------------------------------------------------------
        // More ALU Control Unit tests jere
        // -------------------------------------------------------
 // R-type OR  (funct=0x25)
        test_case(32'h00000025, 32'h00000011, 32'h0000FF00,
                  1'b0, 32'h0000FF11, 1'b1, 1'b0, 1'b0, 1'b0, 2'b10, 1'b0, 1'b0, 1'b1);

        // R-type ADD (funct=0x20)
        test_case(32'h00000020, 32'h00000001, 32'h00000002,
                  1'b0, 32'h00000003, 1'b1, 1'b0, 1'b0, 1'b0, 2'b10, 1'b0, 1'b0, 1'b1);

        // R-type SUB (funct=0x22)
        test_case(32'h00000022, 32'h00000005, 32'h00000003,
                  1'b0, 32'h00000002, 1'b1, 1'b0, 1'b0, 1'b0, 2'b10, 1'b0, 1'b0, 1'b1);

        // R-type SLT (funct=0x2A)
        test_case(32'h0000002A, 32'h00000002, 32'h00000005,
                  1'b0, 32'h00000001, 1'b1, 1'b0, 1'b0, 1'b0, 2'b10, 1'b0, 1'b0, 1'b1);

        // R-type NOR (funct=0x27)
        test_case(32'h00000027, 32'hAAAA5555, 32'h12345678,
                  1'b0, ~(32'hAAAA5555 | 32'h12345678), 1'b1, 1'b0, 1'b0, 1'b0, 2'b10, 1'b0, 1'b0, 1'b1);

        // --------------------------------------------------------------
        // End testing
        // --------------------------------------------------------------
        $write("\n--------------------------------------------------------------");
        $write("\nTesting complete\nPassed %0d / %0d tests",totalTests-failedTests,totalTests);
        $write("\n--------------------------------------------------------------\n");
        $finish();
    end
endmodule

lab03.vcd
$date
	Mon May  5 06:37:51 2025
$end
$version
	Icarus Verilog
$end
$timescale
	1ps
$end
$scope module datapath_tb $end
$var wire 1 ! zero $end
$var wire 32 " result [31:0] $end
$var wire 1 # reg_write $end
$var wire 1 $ reg_dst $end
$var wire 1 % mem_write $end
$var wire 1 & mem_to_reg $end
$var wire 1 ' mem_read $end
$var wire 1 ( branch $end
$var wire 1 ) alu_src $end
$var wire 2 * alu_op [1:0] $end
$var wire 4 + alu_ctrl [3:0] $end
$var reg 32 , A [31:0] $end
$var reg 32 - B [31:0] $end
$var reg 1 . clk $end
$var reg 32 / instruction [31:0] $end
$var integer 32 0 failedTests [31:0] $end
$var integer 32 1 totalTests [31:0] $end
$scope module alu_control_uut $end
$var wire 6 2 funct [5:0] $end
$var wire 2 3 alu_op [1:0] $end
$var reg 4 4 alu_control [3:0] $end
$upscope $end
$scope module alu_uut $end
$var wire 32 5 A [31:0] $end
$var wire 32 6 B [31:0] $end
$var wire 4 7 alu_control [3:0] $end
$var reg 32 8 result [31:0] $end
$var reg 1 ! zero $end
$upscope $end
$scope module control_uut $end
$var wire 6 9 instr_op [5:0] $end
$var reg 2 : alu_op [1:0] $end
$var reg 1 ) alu_src $end
$var reg 1 ( branch $end
$var reg 1 ' mem_read $end
$var reg 1 & mem_to_reg $end
$var reg 1 % mem_write $end
$var reg 1 $ reg_dst $end
$var reg 1 # reg_write $end
$upscope $end
$scope task test_case $end
$var reg 32 ; A_val [31:0] $end
$var reg 32 < B_val [31:0] $end
$var reg 2 = alu_op_val [1:0] $end
$var reg 1 > alu_src_val $end
$var reg 1 ? branch_val $end
$var reg 32 @ instruction_val [31:0] $end
$var reg 1 A mem_read_val $end
$var reg 1 B mem_to_reg_val $end
$var reg 1 C mem_write_val $end
$var reg 1 D reg_dst_val $end
$var reg 1 E reg_write_val $end
$var reg 32 F result_val [31:0] $end
$var reg 1 G zero_val $end
$upscope $end
$upscope $end
$enddefinitions $end
$comment Show the parameter values. $end
$dumpall
$end
#0
$dumpvars
xG
bx F
xE
xD
xC
xB
xA
bx @
x?
x>
bx =
bx <
bx ;
bx :
bx 9
bx 8
bx 7
bx 6
bx 5
bx 4
bx 3
bx 2
b0 1
b0 0
bx /
0.
bx -
bx ,
bx +
bx *
x)
x(
x'
x&
x%
x$
x#
bx "
x!
$end
#50000
1.
#60000
b10 *
b10 3
b10 :
0(
0%
0'
1#
0&
0)
1$
b0 +
b0 4
b0 7
0!
b1 "
b1 8
b0 9
b100100 2
b1 -
b1 6
b11111111111111111111111111111111 ,
b11111111111111111111111111111111 5
b100100 /
b1 1
1E
0>
0C
b10 =
0B
0A
0?
1D
b1 F
0G
b1 <
b11111111111111111111111111111111 ;
b100100 @
#100000
0.
#150000
1.
#170000
b11111111111111111111111111111111 "
b11111111111111111111111111111111 8
b1 +
b1 4
b1 7
b100101 2
b100101 /
b10 1
b11111111111111111111111111111111 F
b100101 @
#200000
0.
#250000
1.
#280000
1!
b0 "
b0 8
b10 +
b10 4
b10 7
b100000 2
b100000 /
b11 1
b0 F
1G
b100000 @
#300000
0.
#350000
1.
#390000
0!
b11111111111111111111111111111110 "
b11111111111111111111111111111110 8
b110 +
b110 4
b110 7
b100010 2
b100010 /
b100 1
b11111111111111111111111111111110 F
0G
b100010 @
#400000
0.
#450000
1.
#500000
b1 "
b1 8
b111 +
b111 4
b111 7
b101010 2
b101010 /
b101 1
b1 F
b101010 @
0.
#550000
1.
#600000
0.
#610000
b1100 +
b1100 4
b1100 7
1!
b0 "
b0 8
b100111 2
b11111111111111110000000000000000 -
b11111111111111110000000000000000 6
b1111111111111111 ,
b1111111111111111 5
b100111 /
b110 1
b0 F
1G
b11111111111111110000000000000000 <
b1111111111111111 ;
b100111 @
#650000
1.
#700000
0.
#720000
0!
b11111111111111111111111111111111 "
b11111111111111111111111111111111 8
b0 *
b0 3
b0 :
1)
0$
b10 +
b10 4
b10 7
b1000 9
b100 2
b100 -
b100 6
b11111111111111111111111111111011 ,
b11111111111111111111111111111011 5
b100000000000000000000000000100 /
b111 1
1>
b0 =
0D
b11111111111111111111111111111111 F
0G
b100 <
b11111111111111111111111111111011 ;
b100000000000000000000000000100 @
#750000
1.
#800000
0.
#830000
1'
1&
b100011111 "
b100011111 8
b100011 9
b100000 2
b100000 -
b100000 6
b11111111 ,
b11111111 5
b10001100000000000000000000100000 /
b1000 1
1B
1A
b100011111 F
b100000 <
b11111111 ;
b10001100000000000000000000100000 @
#850000
1.
#900000
0.
#940000
1%
0'
0#
0&
b101100011 "
b101100011 8
b101011 9
b100100 2
b1100100 -
b1100100 6
b10101100000000000000000001100100 /
b1001 1
0E
1C
0B
0A
b101100011 F
b1100100 <
b10101100000000000000000001100100 @
#950000
1.
#1000000
0.
#1050000
b110 +
b110 4
b110 7
b1 *
b1 3
b1 :
1(
0%
0)
b11011010 "
b11011010 8
b100 9
b100101 2
b100101 -
b100101 6
b10000000000000000000000100101 /
b1010 1
0>
0C
b1 =
1?
b11011010 F
b100101 <
b10000000000000000000000100101 @
1.
#1100000
0.
#1150000
1.
#1160000
b0 +
b0 4
b0 7
b10 *
b10 3
b10 :
0(
1#
1$
b1 "
b1 8
b0 9
b100100 2
b1 -
b1 6
b11111111111111111111111111111111 ,
b11111111111111111111111111111111 5
b100100 /
b1011 1
1E
b10 =
0?
1D
b1 F
b1 <
b11111111111111111111111111111111 ;
b100100 @
#1200000
0.
#1250000
1.
#1270000
b1 +
b1 4
b1 7
0!
b1111111100010001 "
b1111111100010001 8
b100101 2
b1111111100000000 -
b1111111100000000 6
b10001 ,
b10001 5
b100101 /
b1100 1
b1111111100010001 F
b1111111100000000 <
b10001 ;
b100101 @
#1300000
0.
#1350000
1.
#1380000
b10 +
b10 4
b10 7
b11 "
b11 8
b100000 2
b10 -
b10 6
b1 ,
b1 5
b100000 /
b1101 1
b11 F
b10 <
b1 ;
b100000 @
#1400000
0.
#1450000
1.
#1490000
b110 +
b110 4
b110 7
b10 "
b10 8
b100010 2
b11 -
b11 6
b101 ,
b101 5
b100010 /
b1110 1
b10 F
b11 <
b101 ;
b100010 @
#1500000
0.
#1550000
1.
#1600000
b111 +
b111 4
b111 7
b1 "
b1 8
b101010 2
b101 -
b101 6
b10 ,
b10 5
b101010 /
b1111 1
b1 F
b101 <
b10 ;
b101010 @
0.
#1650000
1.
#1700000
0.
#1710000
b1000101010000011010100010000010 "
b1000101010000011010100010000010 8
b1100 +
b1100 4
b1100 7
b100111 2
b10010001101000101011001111000 -
b10010001101000101011001111000 6
b10101010101010100101010101010101 ,
b10101010101010100101010101010101 5
b100111 /
b10000 1
b1000101010000011010100010000010 F
b10010001101000101011001111000 <
b10101010101010100101010101010101 ;
b100111 @
